cleablade_cloud_iot-0.0.0-py3.8-nspkg.pth
clearblade/cloud/iot_v1/__init__.py
clearblade/cloud/iot_v1/client.py
clearblade/cloud/iot_v1/config.py
clearblade/cloud/iot_v1/config_manager.py
clearblade/cloud/iot_v1/developer_tests.py
clearblade/cloud/iot_v1/device_types.py
clearblade/cloud/iot_v1/devices.py
clearblade/cloud/iot_v1/exceptions.py
clearblade/cloud/iot_v1/http_client.py
clearblade/cloud/iot_v1/pagers.py
clearblade/cloud/iot_v1/registry.py
clearblade/cloud/iot_v1/registry_types.py
clearblade/cloud/iot_v1/utils.py
cleablade_cloud_iot-0.0.0.dist-info/LICENSE
cleablade_cloud_iot-0.0.0.dist-info/METADATA
cleablade_cloud_iot-0.0.0.dist-info/WHEEL
cleablade_cloud_iot-0.0.0.dist-info/namespace_packages.txt
cleablade_cloud_iot-0.0.0.dist-info/top_level.txt
cleablade_cloud_iot-0.0.0.dist-info/RECORD
