Metadata-Version: 2.1
Name: cleablade-cloud-iot
Version: 0.0.0
Summary: Cloud IoT API client library
Home-page: https://github.com/clearblade/python-iot
Author: Clearblade
Author-email: googleapis-packages@oogle.com
License: Apache 2.0
Platform: Posix; MacOS X; Windows
Classifier: Development Status :: 5 - Production/Stable
Classifier: Intended Audience :: Developers
Classifier: License :: OSI Approved :: Apache Software License
Classifier: Programming Language :: Python
Classifier: Programming Language :: Python :: 3
Classifier: Programming Language :: Python :: 3.7
Classifier: Programming Language :: Python :: 3.8
Classifier: Programming Language :: Python :: 3.9
Classifier: Programming Language :: Python :: 3.10
Classifier: Operating System :: OS Independent
Classifier: Topic :: Internet
Requires-Python: >=3.7
Requires-Dist: httpx
